LICENSE
MANIFEST.in
README.md
requirements.txt
setup.py
hpc2ml/__init__.py
hpc2ml.egg-info/PKG-INFO
hpc2ml.egg-info/SOURCES.txt
hpc2ml.egg-info/dependency_links.txt
hpc2ml.egg-info/requires.txt
hpc2ml.egg-info/top_level.txt
hpc2ml/data/__init__.py
hpc2ml/data/batchdata.py
hpc2ml/data/dataset.py
hpc2ml/data/structuretodata.py
hpc2ml/data/embedding/__init__.py
hpc2ml/data/embedding/cohesive_energy.py
hpc2ml/data/embedding/continuous_embeddings.py
hpc2ml/data/io/__init__.py
hpc2ml/data/io/ase.py
hpc2ml/data/io/asedb.py
hpc2ml/data/io/main.py
hpc2ml/data/io/pmgjson.py
hpc2ml/data/io/table.py
hpc2ml/data/io/vasp.py
hpc2ml/data/nequlip_support/AtomicDataDict.py
hpc2ml/data/nequlip_support/__init__.py
hpc2ml/data/nequlip_support/_irrreps_support.py
hpc2ml/data/nequlip_support/_keys.py
hpc2ml/data/nequlip_support/_transforms.py
hpc2ml/data/nequlip_support/fields.py
hpc2ml/data/nequlip_support/typing.py
hpc2ml/data/preprocessing/__init__.py
hpc2ml/data/preprocessing/pack.py
hpc2ml/data/preprocessing/structure_matcher.py
hpc2ml/data/sampler/__init__.py
hpc2ml/data/sampler/random_group_sampler.py
hpc2ml/db/__init__.py
hpc2ml/db/ase_db_extension/__init__.py
hpc2ml/db/ase_db_extension/ext_db.py
hpc2ml/db/ase_db_extension/ext_db_csv.py
hpc2ml/db/ase_db_extension/ext_row.py
hpc2ml/function/__init__.py
hpc2ml/function/support.py
hpc2ml/nn/__init__.py
hpc2ml/nn/activations.py
hpc2ml/nn/basis.py
hpc2ml/nn/cggru.py
hpc2ml/nn/cggruforce.py
hpc2ml/nn/cggruforcestress.py
hpc2ml/nn/flow_geo.py
hpc2ml/nn/forces.py
hpc2ml/nn/general.py
hpc2ml/nn/lj.py
hpc2ml/nn/metrics.py
hpc2ml/nn/morse.py
hpc2ml/nn/resnet.py
hpc2ml/nn/stress.py
hpc2ml/nn/templatemodel.py
hpc2ml/nn/nequlipnn/__init__.py
hpc2ml/nn/nequlipnn/model/__init__.py
hpc2ml/nn/nequlipnn/model/_eng.py
hpc2ml/nn/nequlipnn/model/_grads.py
hpc2ml/nn/nequlipnn/model/e3net.py
hpc2ml/nn/nequlipnn/nn/__init__.py
hpc2ml/nn/nequlipnn/nn/_atomwise.py
hpc2ml/nn/nequlipnn/nn/_concat.py
hpc2ml/nn/nequlipnn/nn/_convnetlayer.py
hpc2ml/nn/nequlipnn/nn/_grad_output.py
hpc2ml/nn/nequlipnn/nn/_graph_mixin.py
hpc2ml/nn/nequlipnn/nn/_interaction_block.py
hpc2ml/nn/nequlipnn/nn/_linear.py
